[
    {
        "date": "2023-06-03",
        "lieu": "Rouvroy",
        "positions": [
            [
                50.393427,
                2.903673
            ]
        ],
        "nbPersonnes": 9,
        "type": "marche aux puces",
        "description": "La marche c'est l'pied a organisé ce samedi 03 Juin 2023 son marché aux puces au rendez vous le beau temps dans une très bonne ambiance. 🤩🤩 Un grand merci aux bénévoles qui étaient présent Christian, Patricia, Léa, Romain, André, Monique, Isabelle, Domy, Valérie. Rendez vous l'année prochaine 😉😉😉",
        "photos": [
            "https://i.imgur.com/OdW9nu4.jpg"
        ]
    },
    {
        "date": "2023-04-16",
        "lieu": "Rouvroy",
        "positions": [
            [
                50.393427,
                2.903673
            ]
        ],
        "nbPersonnes": 12,
        "type": "interclub personnel",
        "description": "Voici les photos de notre interclub. Merci aux 217 marcheurs et un grand merci aux bénévoles pour leur implication dans la joie et la bonne humeur après l'effort le réconfort pour le club repas sandwich 😉rendez vous l'année prochaine.",
        "photos": [
            "https://i.imgur.com/ogRakMD.jpg",
            "https://i.imgur.com/36x4xYK.jpg",
            "https://i.imgur.com/Hy1tc83.jpg",
            "https://i.imgur.com/rw3qVKI.jpg",
            "https://i.imgur.com/JGhIsfV.jpg",
            "https://i.imgur.com/EYUtWEF.jpg",
            "https://i.imgur.com/pCUUFNI.jpg",
            "https://i.imgur.com/OOKG330.jpg",
            "https://i.imgur.com/8pioYYK.jpg",
            "https://i.imgur.com/xnPkvPg.jpg",
            "https://i.imgur.com/WBVw9mL.jpg",
            "https://i.imgur.com/O46n52e.jpg",
            "https://i.imgur.com/VyePod7.jpg",
            "https://i.imgur.com/EWccRW1.jpg",
            "https://i.imgur.com/60B930Q.jpg",
            "https://i.imgur.com/YTVnb2t.jpg",
            "https://i.imgur.com/TTocfEH.jpg",
            "https://i.imgur.com/DUIttDh.jpg",
            "https://i.imgur.com/P7f6wVf.jpg",
            "https://i.imgur.com/PLgWuL6.jpg",
            "https://i.imgur.com/P0Wl0R7.jpg",
            "https://i.imgur.com/RW7R0vf.jpg",
            "https://i.imgur.com/bNSHb0f.jpg",
            "https://i.imgur.com/N76BVqA.jpg",
            "https://i.imgur.com/wCWOMck.jpg",
            "https://i.imgur.com/XFcnpg7.jpg",
            "https://i.imgur.com/WYWZ2v6.jpg",
            "https://i.imgur.com/KIqoz36.jpg",
            "https://i.imgur.com/D572Wjq.jpg",
            "https://i.imgur.com/q81USHH.jpg",
            "https://i.imgur.com/ULWPfxD.jpg",
            "https://i.imgur.com/gzfZPhi.jpg",
            "https://i.imgur.com/vP5869i.jpg",
            "https://i.imgur.com/zvPaWhT.jpg",
            "https://i.imgur.com/l6KCmkj.jpg",
            "https://i.imgur.com/j08A2IO.jpg",
            "https://i.imgur.com/mTcgXAl.jpg",
            "https://i.imgur.com/ktsQCk8.jpg",
            "https://i.imgur.com/bLoCSF4.jpg",
            "https://i.imgur.com/iXm6jl1.jpg",
            "https://i.imgur.com/9Np24YD.jpg",
            "https://i.imgur.com/9AYAOfx.jpg",
            "https://i.imgur.com/0aOHbuv.jpg",
            "https://i.imgur.com/4q2PIAJ.jpg",
            "https://i.imgur.com/zcfWtsh.jpg",
            "https://i.imgur.com/pwCs0iT.jpg",
            "https://i.imgur.com/n6r09qE.jpg",
            "https://i.imgur.com/jgBI84p.jpg",
            "https://i.imgur.com/RkFmxS7.jpg",
            "https://i.imgur.com/oNsu83d.jpg",
            "https://i.imgur.com/XXgu0Bn.jpg",
            "https://i.imgur.com/m9VZ6DX.jpg",
            "https://i.imgur.com/a233KCl.jpg",
            "https://i.imgur.com/8oE5T0z.jpg",
            "https://i.imgur.com/QRuBt1q.jpg",
            "https://i.imgur.com/vT6XBaV.jpg",
            "https://i.imgur.com/aTGnmRl.jpg",
            "https://i.imgur.com/B5B2Ugp.jpg",
            "https://i.imgur.com/JOJov9k.jpg",
            "https://i.imgur.com/5PGU6uY.jpg",
            "https://i.imgur.com/oandwyX.jpg",
            "https://i.imgur.com/gmPDZss.jpg",
            "https://i.imgur.com/r6R3vxk.jpg",
            "https://i.imgur.com/9DnF5OO.jpg",
            "https://i.imgur.com/kX48LNw.jpg",
            "https://i.imgur.com/AOJa5tC.jpg",
            "https://i.imgur.com/ihiCy7j.jpg",
            "https://i.imgur.com/bqR3KoZ.jpg",
            "https://i.imgur.com/apgvm0T.jpg",
            "https://i.imgur.com/oPWzry6.jpg",
            "https://i.imgur.com/B8f7wVc.jpg",
            "https://i.imgur.com/l9PDzWC.jpg",
            "https://i.imgur.com/VXDR99l.jpg",
            "https://i.imgur.com/aioHeoT.jpg",
            "https://i.imgur.com/E7CBiiL.jpg",
            "https://i.imgur.com/2VSfZtX.jpg",
            "https://i.imgur.com/zjyRyVY.jpg",
            "https://i.imgur.com/M8F04yD.jpg",
            "https://i.imgur.com/peZOVnY.jpg",
            "https://i.imgur.com/OgLCODq.jpg"
        ]
    }
]